[
    {
        "directory": "60seconds",
        "url": "/projects/60seconds",
        "name": {
            "en": "60seconds",
            "fi": "60seconds"
        },
        "date": 100
    },
    {
        "directory": "a-clock",
        "url": "/projects/a-clock",
        "name": {
            "en": "a clock",
            "fi": "a clock"
        },
        "icon": "/projects/a-clock/icon.png",
        "date": 1571086800000
    },
    {
        "directory": "adventuresofuggelbuggel",
        "url": "/projects/adventuresofuggelbuggel",
        "name": {
            "en": "Adventures of Uggel Buggel",
            "fi": "Adventures of Uggel Buggel"
        },
        "description": {
            "en": "School project. Javascript game built with construct 2",
            "fi": "Koulutyö. Javascript peli rakennettu construct 2 ohjelmalla"
        },
        "icon": "/projects/adventuresofuggelbuggel/icon-114.png",
        "date": 1512079200000
    },
    {
        "directory": "automatic-giorgio",
        "url": "/projects/automatic-giorgio",
        "name": {
            "en": "Automatic Giorgio",
            "fi": "Automatic Giorgio"
        },
        "description": {
            "en": "Random animated art with changing music",
            "fi": "Satunnaistettua graafista näkymää vaihtuvalla musiikilla"
        },
        "icon": "/projects/automatic-giorgio/icon.png",
        "date": 1602277200000
    },
    {
        "directory": "countdown",
        "url": "/projects/countdown",
        "name": {
            "en": "countdown",
            "fi": "countdown"
        },
        "date": 100
    },
    {
        "directory": "cursors",
        "url": "/projects/cursors",
        "name": {
            "en": "cursors",
            "fi": "cursors"
        },
        "date": 100
    },
    {
        "directory": "firework",
        "url": "/projects/firework",
        "name": {
            "en": "Firework",
            "fi": "Firework"
        },
        "description": {
            "en": "Canvas fireworks.",
            "fi": "Raketteja."
        },
        "icon": "/projects/firework/icon.png",
        "date": 1561928400000
    },
    {
        "directory": "gameoflife",
        "url": "/projects/gameoflife",
        "name": {
            "en": "Game of life",
            "fi": "Game of life"
        },
        "description": {
            "en": "Convay's game of life built with check boxes",
            "fi": "Convayn Game Of Life. Rajapintana napit"
        },
        "icon": "/projects/gameoflife/icon.png",
        "date": 1593810000000
    },
    {
        "directory": "hedelmapeli",
        "url": "/projects/hedelmapeli",
        "name": {
            "en": "Slots machine",
            "fi": "Slots machine"
        },
        "description": {
            "en": "School project. Very basic slotmachine",
            "fi": "Koulutyö. Todella yksinkertainen hedelmäpeli"
        },
        "icon": "/projects/hedelmapeli/icon.png",
        "date": 1539464400000
    },
    {
        "directory": "ivs",
        "url": "/projects/ivs",
        "name": {
            "en": "Air Surveillance narration",
            "fi": "Ilmavalvontaseloste"
        },
        "icon": "/projects/ivs/icon.png",
        "date": 1604440800000
    },
    {
        "directory": "jutinrillimakkarapeli",
        "url": "/projects/jutinrillimakkarapeli",
        "name": {
            "en": "Juti's Grilling Game",
            "fi": "Jutin grillimakkarapeli"
        },
        "description": {
            "en": "an inside joke. Homage to 'Sakarin villapaitapeli'",
            "fi": "Inside vitsi. Kunnianosoitus Sakarin villapaitapelille"
        },
        "icon": "/projects/jutinrillimakkarapeli/icon.png",
        "date": 1527800400000
    },
    {
        "directory": "kalastuspeli",
        "url": "/projects/kalastuspeli",
        "name": {
            "en": "kalastuspeli",
            "fi": "kalastuspeli"
        },
        "date": 100
    },
    {
        "directory": "karanteeni",
        "url": "http://karanteeni.net/",
        "custom_url": true,
        "name": {
            "en": "Karanteeni Website",
            "fi": "Karanteeni"
        },
        "description": {
            "en": "Website for the finnish minecraft community Karanteeni",
            "fi": "Verkkosivusto suomalaiselle minecraft yhteisölle"
        },
        "icon": "/projects/karanteeni/icon.png",
        "date": 1564606800000
    },
    {
        "directory": "karanteeni-discord",
        "url": "https://github.com/Pennane/karanteeni-discord",
        "custom_url": true,
        "name": {
            "en": "Karanteeni Overseer",
            "fi": "Karanteeni Overseer"
        },
        "description": {
            "en": "Discord moderation and utility service",
            "fi": "Discord moderation and utility service"
        },
        "icon": "/projects/karanteeni-discord/icon-144.png",
        "date": 1599944400000
    },
    {
        "directory": "karanteeni-joulu",
        "url": "https://github.com/Pennane/korsoraattori-extension/releases",
        "custom_url": true,
        "name": {
            "en": "Karanteeni Advent Calendar 2019",
            "fi": "Karanteenin joulukalenteri 2019"
        },
        "description": {
            "en": "Interactive advent calendar for a minecraft community",
            "fi": "Interaktiivinen minecraft yhteisön joulukalenteri"
        },
        "date": 1574978400000
    },
    {
        "directory": "korsoraattori",
        "url": "https://github.com/Pennane/korsoraattori-extension/releases",
        "custom_url": true,
        "name": {
            "en": "Korsoraattori Chrome Extension",
            "fi": "Korsoraattori Chrome Extension"
        },
        "description": {
            "en": "Korsoraattori wrapped as a Chrome extension",
            "fi": "Korsoraattori kääritty Chrome laajennukseksi"
        },
        "date": 1612476000000
    },
    {
        "directory": "landing-page-demo",
        "url": "/projects/landing-page-demo",
        "name": {
            "en": "landing-page-demo",
            "fi": "landing-page-demo"
        },
        "date": 100
    },
    {
        "directory": "laser",
        "url": "/projects/laser",
        "name": {
            "en": "Scientific laser refraction & reflection",
            "fi": "Laserin hajonta & heijastus"
        },
        "description": {
            "en": "a School project",
            "fi": "Koulutyö"
        },
        "icon": "/projects/laser/icon.png",
        "date": 1538859600000
    },
    {
        "directory": "lottotodennakoisyys",
        "url": "/projects/lottotodennakoisyys",
        "name": {
            "en": "Lottery Probability Simulator",
            "fi": "Lottotodennäköisyys simulaattori"
        },
        "description": {
            "en": "Site that simulates money gain using Veikkaus lottery service",
            "fi": "Sivu joka simuloi tuloja peletessa Veikkauksen lottoa"
        },
        "icon": "/projects/lottotodennakoisyys/icon.png",
        "date": 1541023200000
    },
    {
        "directory": "mc-rgb-gradient",
        "url": "/projects/mc-rgb-gradient",
        "name": {
            "en": "Minecraft nickname generator",
            "fi": "Minecraft nickname generator"
        },
        "description": {
            "en": "Transform color gradient and a name into a nickname",
            "fi": "Transform color gradient and a name into a nickname"
        },
        "date": 1578434400000
    },
    {
        "directory": "minesweeper",
        "url": "https://minesweeper.pennanen.dev",
        "custom_url": true,
        "name": {
            "en": "Minesweeper",
            "fi": "Miinaharava"
        },
        "description": {
            "en": "Traditional minesweeper built with Vue",
            "fi": "Tavanomainen miinaharava"
        },
        "icon": "/projects/minesweeper/icon.png",
        "date": 1609884000000
    },
    {
        "directory": "peigom",
        "url": "https://peigom.pennanen.dev",
        "custom_url": true,
        "name": {
            "en": "Peigom",
            "fi": "Peigom"
        },
        "description": {
            "en": "Hardwired Discord multi-utility bot",
            "fi": "Discord bot suurella kourallisella ominaisuuksia ja inside vitsejä"
        },
        "icon": "/projects/peigom/icon.png",
        "date": 1549749600000
    },
    {
        "directory": "peigom-bot_opas",
        "url": "/projects/peigom-bot_opas",
        "name": {
            "en": "peigom-bot_opas",
            "fi": "peigom-bot_opas"
        },
        "date": 100
    },
    {
        "directory": "perception",
        "url": "/projects/perception",
        "name": {
            "en": "Color perception",
            "fi": "Värihavannointi"
        },
        "description": {
            "en": "Demo that conveys human eyesight",
            "fi": "Demo joka havaoinnoi silmnän käyttäytymistä"
        },
        "date": 1536267600000
    },
    {
        "directory": "pokeri_kadet",
        "url": "/projects/pokeri_kadet",
        "name": {
            "en": "pokeri_kadet",
            "fi": "pokeri_kadet"
        },
        "date": 100
    },
    {
        "directory": "rankitdemo",
        "url": "/projects/rankitdemo",
        "name": {
            "en": "rankitdemo",
            "fi": "rankitdemo"
        },
        "date": 100
    },
    {
        "directory": "raymarching",
        "url": "/projects/raymarching",
        "name": {
            "en": "Raymarching",
            "fi": "Raymarching"
        },
        "description": {
            "en": "Raymarching demo",
            "fi": "2D etäisyyden etsimis demo"
        },
        "date": 1565730000000
    },
    {
        "directory": "rotmg_fame",
        "url": "/projects/rotmg_fame",
        "name": {
            "en": "rotmg_fame",
            "fi": "rotmg_fame"
        },
        "date": 100
    },
    {
        "directory": "sanaetsuri",
        "url": "/projects/sanaetsuri",
        "name": {
            "en": "Wordsnack word finder",
            "fi": "Sanaetsuri"
        },
        "description": {
            "en": "Word finder for the mobile game word snack",
            "fi": "Sanojen etsijä Sanapala mobiilipeliin"
        },
        "icon": "/projects/sanaetsuri/icon.png",
        "date": 1588280400000
    },
    {
        "directory": "spotify-favorites",
        "url": "https://spotifyfavorites.pennanen.dev/",
        "custom_url": true,
        "name": {
            "en": "Spotify Favorites",
            "fi": "Spotify Favorites"
        },
        "description": {
            "en": "Spotify listening history analytics",
            "fi": "Spotify kuuntelu analytiikkaa"
        },
        "date": 1575928800000
    },
    {
        "directory": "thinkingscreensaver",
        "url": "/projects/thinkingscreensaver",
        "name": {
            "en": "Thinking screensaver",
            "fi": "Thinking screensaver"
        },
        "description": {
            "en": "Out of touch screensaver",
            "fi": "Ajankohtainen näytönsäästäjä"
        },
        "icon": "/projects/thinkingscreensaver/icon.png",
        "date": 1548367200000
    },
    {
        "directory": "thonketspinner",
        "url": "/projects/thonketspinner",
        "name": {
            "en": "thonketspinner",
            "fi": "thonketspinner"
        },
        "date": 100
    },
    {
        "directory": "thonkpaint",
        "url": "/projects/thonkpaint",
        "name": {
            "en": "Thonkpaint",
            "fi": "Thonkpaint"
        },
        "description": {
            "en": "Different kind of paint",
            "fi": "Erilainen Paint"
        },
        "date": 1525122000000
    },
    {
        "directory": "truewave",
        "url": "/projects/truewave",
        "name": {
            "en": "truewave",
            "fi": "truewave"
        },
        "date": 100
    },
    {
        "directory": "typechase",
        "url": "/projects/typechase",
        "name": {
            "en": "Typechase",
            "fi": "Typechase"
        },
        "description": {
            "en": "Typing speed application",
            "fi": "Konekirjoitussovellus"
        },
        "icon": "/projects/typechase/icon.png",
        "date": 1562014800000
    },
    {
        "directory": "waveanimation",
        "url": "/projects/waveanimation",
        "name": {
            "en": "waveanimation",
            "fi": "waveanimation"
        },
        "date": 100
    },
    {
        "directory": "yatzy",
        "url": "https://yatzy.pennanen.dev/",
        "custom_url": true,
        "name": {
            "en": "Yatzy die game",
            "fi": "Yatzy"
        },
        "description": {
            "en": "A traditional die game built with Vue",
            "fi": "Perinteinen Yatzy peli. Rakennettu Vue:lla."
        },
        "icon": "/projects/yatzy/icon.png",
        "date": 1577829600000
    },
    {
        "directory": "yla-aste_html",
        "url": "/projects/yla-aste_html",
        "name": {
            "en": "yla-aste_html",
            "fi": "yla-aste_html"
        },
        "date": 100
    }
]